tracuni/__init__.py
tracuni/adapter.py
tracuni/adapter_tornado.py
tracuni/cli.py
tracuni/intercept.py
tracuni/define/__init__.py
tracuni/define/const.py
tracuni/define/errors.py
tracuni/define/type.py
tracuni/misc/__init__.py
tracuni/misc/helper.py
tracuni/misc/keep_tornado.py
tracuni/misc/select_coroutine.py
tracuni/point/__init__.py
tracuni/point/accessor.py
tracuni/point/span_general.py
tracuni/point/span_stages.py
tracuni/schema/__init__.py
tracuni/schema/pipe_methods.py
tracuni/schema/shared_rules.py
tracuni/schema/standard.py
tracuni/schema/builtin/__init__.py
tracuni/schema/builtin/core/__init__.py
tracuni/schema/builtin/core/ext_amqp_in.py
tracuni/schema/builtin/core/ext_amqp_out.py
tracuni/schema/builtin/core/ext_db_out.py
tracuni/schema/builtin/core/ext_http_in.py
tracuni/schema/builtin/core/ext_http_in_headers.py
tracuni/schema/builtin/core/ext_http_out.py
tracuni/schema/builtin/core/ext_retry_out.py
tracuni/schema/builtin/tornado/__init__.py
tracuni/schema/builtin/tornado/ext_amqp_out.py
tracuni/schema/builtin/tornado/ext_db_out.py
tracuni/schema/builtin/tornado/ext_http_in.py
tracuni/schema/builtin/tornado/ext_http_out.py
tracuni/schema/builtin/tornado/ext_inner_retry_in.py
tracuni/schema/builtin/tornado/ext_inner_retry_out.py
tracuni/schema/builtin/tornado/log_out.py
tracuni/schema/engine/__init__.py
tracuni/schema/engine/engine.py
tracuni/schema/engine/feed.py
tracuni/schema/engine/pool.py
tracuni/schema/lib/__init__.py
tracuni/schema/lib/catch_essential.py
tracuni/schema/lib/debug.py
tracuni/schema/lib/make_cut.py
tracuni/schema/lib/mask_secret.py
tracuni/schema/lib/pick_items.py
tracuni/side_steps/__init__.py
tracuni/side_steps/db_logger/__init__.py
tracuni/side_steps/db_logger/logger.py
tracuni/side_steps/stat/__init__.py
tracuni/side_steps/stat/adapter.py
tracuni/side_steps/stat/send.py
tracuni-0.4.17.dist-info/METADATA
tracuni-0.4.17.dist-info/WHEEL
tracuni-0.4.17.dist-info/entry_points.txt
tracuni-0.4.17.dist-info/top_level.txt
tracuni-0.4.17.dist-info/RECORD
