Metadata-Version: 2.1
Name: tracuni
Version: 0.4.17
Summary: Convenient library to plug in tracer to incoming and outgoing points and extract data from there
Home-page: https://github.com/hastly/tracuni
Author: Konstantin Gonciarou
Author-email: konstantin.goncharov@inplat.ru
Keywords: jaeger zipkin tracer
Classifier: Development Status :: 2 - Pre-Alpha
Classifier: Intended Audience :: Developers
Classifier: Natural Language :: Russian
Classifier: Programming Language :: Python :: 3
Classifier: Programming Language :: Python :: 3.5
Classifier: Programming Language :: Python :: 3.6
Classifier: Programming Language :: Python :: 3.7
Classifier: Programming Language :: Python :: 3.8
Requires-Python: >=3.5.3
Requires-Dist: aiozipkin (==1.1.1)
Requires-Dist: aiotask-context
Requires-Dist: python-statsd
Requires-Dist: pytz
Requires-Dist: aioamqp
Requires-Dist: typing ; python_version < "3.6"
